groundx/__init__.py
groundx/buckets/__init__.py
groundx/buckets/client.py
groundx/buckets/raw_client.py
groundx/client.py
groundx/core/__init__.py
groundx/core/api_error.py
groundx/core/client_wrapper.py
groundx/core/datetime_utils.py
groundx/core/file.py
groundx/core/force_multipart.py
groundx/core/http_client.py
groundx/core/http_response.py
groundx/core/jsonable_encoder.py
groundx/core/pydantic_utilities.py
groundx/core/query_encoder.py
groundx/core/remove_none_from_dict.py
groundx/core/request_options.py
groundx/core/serialization.py
groundx/csv_splitter.py
groundx/customer/__init__.py
groundx/customer/client.py
groundx/customer/raw_client.py
groundx/documents/__init__.py
groundx/documents/client.py
groundx/documents/raw_client.py
groundx/environment.py
groundx/errors/__init__.py
groundx/errors/bad_request_error.py
groundx/errors/unauthorized_error.py
groundx/extract/__init__.py
groundx/extract/agents/__init__.py
groundx/extract/agents/agent.py
groundx/extract/classes/__init__.py
groundx/extract/classes/agent.py
groundx/extract/classes/api.py
groundx/extract/classes/document.py
groundx/extract/classes/element.py
groundx/extract/classes/field.py
groundx/extract/classes/groundx.py
groundx/extract/classes/group.py
groundx/extract/classes/prompt.py
groundx/extract/classes/test_document.py
groundx/extract/classes/test_field.py
groundx/extract/classes/test_groundx.py
groundx/extract/classes/test_group.py
groundx/extract/classes/test_prompt.py
groundx/extract/post_process/__init__.py
groundx/extract/post_process/post_process.py
groundx/extract/prompt/__init__.py
groundx/extract/prompt/manager.py
groundx/extract/prompt/object_store.py
groundx/extract/prompt/source.py
groundx/extract/prompt/test_manager.py
groundx/extract/prompt/utility.py
groundx/extract/services/.DS_Store
groundx/extract/services/__init__.py
groundx/extract/services/csv.py
groundx/extract/services/logger.py
groundx/extract/services/logging_cfg.py
groundx/extract/services/ratelimit.py
groundx-3.2.9.dist-info/LICENSE
groundx-3.2.9.dist-info/METADATA
groundx-3.2.9.dist-info/WHEEL
groundx-3.2.9.dist-info/RECORD
