Metadata-Version: 2.1
Name: groundx
Version: 3.2.9
Summary: 
License: MIT
Requires-Python: >=3.8,<4.0
Classifier: Intended Audience :: Developers
Classifier: License :: OSI Approved :: MIT License
Classifier: Operating System :: MacOS
Classifier: Operating System :: Microsoft :: Windows
Classifier: Operating System :: OS Independent
Classifier: Operating System :: POSIX
Classifier: Operating System :: POSIX :: Linux
Classifier: Programming Language :: Python
Classifier: Programming Language :: Python :: 3
Classifier: Programming Language :: Python :: 3.8
Classifier: Programming Language :: Python :: 3.9
Classifier: Programming Language :: Python :: 3.10
Classifier: Programming Language :: Python :: 3.11
Classifier: Programming Language :: Python :: 3.12
Classifier: Topic :: Software Development :: Libraries :: Python Modules
Classifier: Typing :: Typed
Provides-Extra: extract
Requires-Dist: aiohttp (>=3.8.0)
Requires-Dist: boto3 ; extra == "extract"
Requires-Dist: celery ; extra == "extract"
Requires-Dist: celery-types ; extra == "extract"
Requires-Dist: dateparser ; extra == "extract"
Requires-Dist: fastapi ; extra == "extract"
Requires-Dist: google-api-python-client ; extra == "extract"
Requires-Dist: google-api-python-client-stubs ; extra == "extract"
Requires-Dist: google-auth-stubs ; extra == "extract"
Requires-Dist: gspread ; extra == "extract"
Requires-Dist: httpx (>=0.21.2)
Requires-Dist: minio ; extra == "extract"
Requires-Dist: pillow ; extra == "extract"
Requires-Dist: pydantic (>=1.9.2)
Requires-Dist: pydantic-core (>=2.18.2,<3.0.0)
Requires-Dist: pytest ; extra == "extract"
Requires-Dist: redis ; extra == "extract"
Requires-Dist: requests (>=2.4.0)
Requires-Dist: tqdm (>=4.60.0)
Requires-Dist: types-PyYAML ; extra == "extract"
Requires-Dist: types-boto3 ; extra == "extract"
Requires-Dist: types-dateparser ; extra == "extract"
Requires-Dist: types-tqdm (>=4.60.0)
Requires-Dist: typing_extensions (>=4.0.0)
